 [
  {
    "hotelId":1,
    "hotelName":"bleua",
    "description":"belle vue",
    "price" :203.4,
    "imageURL":"assets/img/hotel-room.jpg",
    "rating":5
  },
  {
    "hotelId":2,
    "hotelName":"Service",
    "description":"service",
    "price":150.4,
    "imageURL":"assets/img/indoors.jpg",
    "rating":4
  },
  {
    "hotelId":3,
    "hotelName":"zone",
    "description":"the service",
    "price":500.4,
    "imageURL":"assets/img/hotel-room.jpg",
    "rating":2.6
  },
  {
    "hotelId":4,
    "hotelName":"bleua",
    "description":"belle vue",
    "price":405.4,
    "imageURL":"assets/img/window.jpg",
    "rating":3
  }
]
